{
  "timestamp_utc": "2026-06-13T11:10:24Z",
  "timestamp_hkt": "2026-06-13T19:10:24+08:00",
  "mode": "analysis_alerting_paper_trading_only",
  "real_trades_executed": false,
  "markets_monitored": [
    "Polymarket Dallas/KDAL Jun 13 and Jun 14 highest temperature",
    "Polymarket Houston/KHOU Jun 13 and Jun 14 highest temperature",
    "Polymarket Los Angeles/KLAX Jun 13 and Jun 14 highest temperature",
    "Polymarket Chicago/KORD Jun 13 highest temperature",
    "Polymarket NYC/KLGA Jun 13 and Jun 14 highest temperature",
    "Polymarket London/EGLC Jun 13 highest temperature",
    "Kalshi Houston Jun 13 daily high temperature"
  ],
  "top_edges": [
    {
      "rank": 1,
      "market": "Polymarket Houston/KHOU Jun 13 92-93F YES",
      "current_price": "20c",
      "implied_probability": 0.20,
      "estimated_fair_value_range": [0.35, 0.47],
      "estimated_edge_range": [0.15, 0.27],
      "confidence": "low",
      "classification": "strong raw represented edge",
      "action": "maintain existing paper positions only"
    },
    {
      "rank": 2,
      "market": "Polymarket Dallas/KDAL Jun 13 96-97F YES",
      "current_price": "9.8c",
      "implied_probability": 0.098,
      "estimated_fair_value_range": [0.18, 0.30],
      "estimated_edge_range": [0.08, 0.20],
      "confidence": "low",
      "classification": "moderate represented edge",
      "action": "maintain PT-20260613-133 only"
    },
    {
      "rank": 3,
      "market": "Polymarket Los Angeles/KLAX Jun 13 74-75F YES",
      "current_price": "11c",
      "implied_probability": 0.11,
      "estimated_fair_value_range": [0.23, 0.34],
      "estimated_edge_range": [0.12, 0.23],
      "confidence": "low",
      "classification": "moderate represented edge",
      "action": "maintain existing Los Angeles Jun 13 positions only"
    },
    {
      "rank": 4,
      "market": "Polymarket Los Angeles/KLAX Jun 14 70-71F YES",
      "current_price": "18c",
      "implied_probability": 0.18,
      "estimated_fair_value_range": [0.30, 0.42],
      "estimated_edge_range": [0.12, 0.24],
      "confidence": "low-to-medium-low",
      "classification": "moderate represented forward-day edge",
      "action": "maintain PT-20260613-138 only"
    },
    {
      "rank": 5,
      "market": "Polymarket London/EGLC Jun 13 23C YES",
      "current_price": "8c",
      "implied_probability": 0.08,
      "estimated_fair_value_range": [0.14, 0.24],
      "estimated_edge_range": [0.06, 0.16],
      "confidence": "low",
      "classification": "weak-to-moderate represented edge",
      "action": "maintain existing London 23C positions only"
    }
  ],
  "recommended_paper_trades": [],
  "maintenance_notes": [
    "No fresh simulated position opened.",
    "No ledger append created because no new paper trade was recommended.",
    "Existing paper positions remain open for tracking."
  ],
  "sources": [
    "https://polymarket.com/weather/high-temperature",
    "https://polymarket.com/event/highest-temperature-in-houston-on-june-13-2026",
    "https://polymarket.com/event/highest-temperature-in-dallas-on-june-13-2026",
    "https://polymarket.com/event/highest-temperature-in-los-angeles-on-june-13-2026",
    "https://polymarket.com/event/highest-temperature-in-los-angeles-on-june-14-2026",
    "https://polymarket.com/event/highest-temperature-in-london-on-june-13-2026",
    "https://kalshi.com/markets/kxhighthou/daily-high-temperature-houston/kxhighthou-26jun13",
    "https://forecast.weather.gov/MapClick.php?lat=32.85416&lon=-96.85506",
    "https://forecast.weather.gov/MapClick.php?textField1=29.65&textField2=-95.28",
    "https://forecast.weather.gov/MapClick.php?lat=33.9425&lon=-118.409",
    "https://forecast.weather.gov/MapClick.php?lat=41.9796&lon=-87.9045",
    "https://forecast.weather.gov/zipcity.php?inputstring=KLGA",
    "https://weather.metoffice.gov.uk/forecast/u10j124jp"
  ]
}
